README
setup.py
WebUndo.egg-info/PKG-INFO
WebUndo.egg-info/SOURCES.txt
WebUndo.egg-info/dependency_links.txt
WebUndo.egg-info/entry_points.txt
WebUndo.egg-info/not-zip-safe
WebUndo.egg-info/top_level.txt
webundo/__init__.py