Metadata-Version: 1.0
Name: WebUndo
Version: 0.1
Summary: Gmail's undo/cancel web feature, for Pylons and other frameworks
Home-page: http://webundo.abourget.net
Author: Alexandre Bourget
Author-email: alex@bourget.cc
License: UNKNOWN
Platform: UNKNOWN
